scraple/TreeCore.py
scraple/Tree_search_engine.py
scraple/__init__.py
scraple/error.py
scraple/extract.py
scraple/pipeline.py
scraple-0.1.1.dist-info/METADATA
scraple-0.1.1.dist-info/WHEEL
scraple-0.1.1.dist-info/licenses/LICENSE
scraple-0.1.1.dist-info/RECORD
