Metadata-Version: 2.1
Name: scraple
Version: 0.1.1
Summary: Simplify web scraping
Project-URL: repository, https://github.com/max-efort/scraple
Project-URL: changelog, https://github.com/max-efort/scraple/releases
Author-email: Jibril <erikfortran@gmail.com>
License: MIT License
License-File: LICENSE
Keywords: CSS,scraping,selector,simple,webscraping
Classifier: Development Status :: 4 - Beta
Classifier: Intended Audience :: Developers
Classifier: License :: OSI Approved :: MIT License
Classifier: Programming Language :: Python :: 3
Classifier: Topic :: Software Development :: Libraries :: Python Modules
Requires-Python: >=3.6
Requires-Dist: beautifulsoup4>=4.0.0
